Workbook

Sheet Mode d'emploi
B2: Sunsoari · Tableau de marges et de gestion
B3: Version du 11/10/2026 · prix de vente repris de Shopify le 11/10/2026 · tarifs Onsha/Sullab : fiche FOB USD Sullab Co., Ltd.
B4: Documents utilisés : grille FOB Sullab/Onsha, pro forma Sullab du 08/05/2026, packing list SUL-0123, grille et commande SHIFT (260528), facture CNR Cosmetics C-2026-0915 et reçu de paiement 0019. Non utilisés : le reçu Sendwave (virement personnel, sans lien avec un achat de stock) et le dépôt INPI (310 €, dépense ponctuelle à passer en charges, pas dans le coût des produits).
B6: CODE COULEUR
B7: Texte bleu = chiffre que tu peux modifier. Fond jaune = à remplir ou à vérifier en priorité. Texte noir = calcul automatique (ne pas toucher). Texte vert = repris d'un autre onglet.
B9: DANS QUEL ORDRE REMPLIR
B10: 1. Paramètres : ton statut TVA, le taux du dollar, tes frais Shopify, ta livraison, ton emballage, tes cotisations.
B11: 2. Import : les vrais (ajoute « UE » en origine pour un fournisseur européen) frais de ta dernière commande fournisseur (fret, transitaire, banque). Ça calcule ton « coefficient d'approche » = combien te coûte vraiment 1 € de marchandise une fois arrivée chez toi.
B12: 3. Tarifs Shift : à compléter avec ta fiche Shift (cases jaunes).
B13: 4. Marges produits : prix de vente, coût de revient, marge par produit et marge si la cliente n'achète que ce produit.
B14: 5. Simulateur commande : compose un panier et vois ce qu'il te reste vraiment.
B15: 6. Seuil de rentabilité : combien de commandes par mois pour couvrir tes frais fixes.
... B23: • Les taux (frais Shopify, cotisations URSSAF, taux de change) changent : vérifie-les dans ton admin Shopify et sur autoentrepreneur.urssaf.fr. Ce tableau ne remplace pas l'avis de ton expert-comptable.

Sheet Paramètres
B2: Paramètres généraux
B4: Paramètre | C4: Valeur | D4: Explication / source
B5: Statut TVA | C5: Assujettie | D5: SAS assujettie à la TVA (ce que tu m'as indiqué) : tu factures la TVA et tu récupères celle de tes achats. « Franchise » seulement si tu n'es pas assujettie.
B6: Taux de TVA | C6: 0.2 | D6: Taux normal en France.
B7: Taux de change : 1 USD = … € | C7: 0.86 | D7: Indicatif. Mets le taux réellement appliqué par ta banque le jour du paiement (relevé bancaire).
B8: Taux de change : 1 KRW = … € | C8: 0.00063 | D8: Indicatif, utile si un fournisseur facture en wons. À mettre à jour.
B9: Palier de prix Onsha/Sullab utilisé | C9: Carton | D9: « Carton » = prix au carton (petites quantités). « MOQ » = prix à partir d'environ 1 000 pièces par référence.
B10: Droits de douane par défaut (achats hors UE) | C10: 0 | D10: 0 % avec l'accord UE-Corée si une déclaration d'origine figure sur la facture. Sinon souvent entre 1,7 % et 6,5 % selon le code douanier (à confirmer par ton transitaire). Pas de droits de douane pour un fournisseur situé dans l'UE.
B11: Frais de paiement Shopify (%) | C11: 0.015 | D11: Exemple : Shopify Payments, forfait Basic, carte européenne. Vérifie dans Shopify > Paramètres > Paiements (PayPal, Klarna et cartes hors UE coûtent plus cher).
B12: Frais de paiement Shopify (fixe par commande) | C12: 0.25 | D12: Même source que ci-dessus.
B13: Charges proportionnelles au CA | C13: 0 | D13: 0 % pour une SAS : pas de cotisations calculées sur le chiffre d'affaires (contrairement à la micro-entreprise). L'impôt sur les sociétés se calcule sur le bénéfice annuel, voir ton expert-comptable.
B14: Ce que TU paies au transporteur par colis (TTC) | C14: 4 | D14: Coût moyen réel d'une étiquette Mondial Relay / Colissimo pour un colis de moins de 1 kg. Exemple : remplace-le par le montant de tes factures transporteur.
B15: Livraison payée par la cliente (TTC) | C15: 5.9 | D15: Repris de tes tarifs Shopify : Mondial Relay 5,90 € (< 1 kg, depuis le 14/10/2026), Colissimo 7,90 € ou 9,90 €. 5,90 € = le cas le plus courant.
B16: Livraison offerte à partir de (TTC) | C16: 80 | D16: France : livraison offerte dès 80 €, non cumulable avec les remises (sauf code exceptionnel). Dès 100 € après remise dans tous les cas.
B17: Emballage : prix d'un lot de cartons (TTC) | C17: 55 | D17: D'après toi : environ 50 à 60 € le lot.
B18: Emballage : nombre de cartons dans le lot | C18: 40 | D18: D'après toi : une quarantaine.
B19: Papier de soie : prix d'un paquet (TTC) | C19: 15 | D19: D'après toi.
B20: Papier de soie : nombre de colis faits avec un paquet | C20: 50 | D20: Estimation à ajuster : combien de colis tu emballes avec un paquet.
B21: Emballage : scotch, étiquette, carte (par colis, TTC) | C21: 0.2 | D21: Estimation.
... B26: Marge minimum acceptable (% du CA) | C26: 0.4 | D26: En dessous, le produit est signalé « marge faible ».
B28: Les frais sont saisis TTC (ce que tu paies). Comme tu récupères la TVA, le tableau les compte automatiquement hors TVA.

Sheet Import
B2: Coût réel d'une commande fournisseur (coefficient d'approche)
B3: Remplace les valeurs d'exemple (jaunes) par celles de ta dernière facture fournisseur et de ta facture transporteur/transitaire.
B5: Ligne | C5: Onsha / Sullab | D5: Shift | E5: CNR Cosmetics | F5: Explication
B6: Valeur de la marchandise (devise du fournisseur) | C6: 3329 | D6: 2285 | E6: 435 | F6: Sullab : facture commerciale SUL-0413 du 13/04/2026 (3 329 $, 492 pièces, 7 cartons, 85 kg). Shift : bon de commande (2 285 $). CNR : facture C-2026-0915 (435 €).
B7: Devise de la facture | C7: USD | D7: USD | E7: EUR | F7: USD, EUR ou KRW.
B8: Origine du fournisseur | C8: Hors UE | D8: Hors UE | E8: Hors UE | F8: « Hors UE » (Corée…) ou « UE ». Un fournisseur de l'UE : pas de droits de douane ni de TVA à l'import (TVA autoliquidée).
B9: Taux de change appliqué | C9: =IF(C7="USD",Paramètres!$C$7,IF(C7="KRW",Paramètres!$C$8,1)) -> 0.86 | D9: =IF(D7="USD",Paramètres!$C$7,IF(D7="KRW",Paramètres!$C$8,1)) -> 0.86 | E9: =IF(E7="USD",Paramètres!$C$7,IF(E7="KRW",Paramètres!$C$8,1)) -> 1 | F9: Repris des Paramètres.
B10: Valeur de la marchandise en € | C10: =C6*C9 -> 2862.94 | D10: =D6*D9 -> 1965.1 | E10: =E6*E9 -> 435
B11: Fret international (€) | C11: =773.61*Paramètres!$C$7 -> 665.3046 | D11: 250 | E11: 20.5 | F11: Sullab : RÉEL, 773,61 $ facturés sur SUL-0413 (reçu EMS de La Poste coréenne : 1 149 350 KRW pour 7 colis), soit 23 % de la marchandise. Shift : estimation à remplacer. CNR : 150 € facturés − 129,5 € pris en charge = 20,5 € (réel).
B12: Assurance transport (€) | C12: 0 | D12: 0 | E12: 0 | F12: Souvent incluse ou optionnelle.
B13: Frais de dédouanement / transitaire (€) | C13: 25 | D13: 40 | E13: 25 | F13: Frais de dossier facturés par La Poste, DHL ou le transitaire à la livraison. Estimations à remplacer. Montants hors TVA.
B14: Frais bancaires du virement international (€) | C14: 30 | D14: 15 | E14: 15 | F14: Sullab : paiement en 2 fois (50/50), donc 2 virements. Shift et CNR : 1 virement (100 % avant expédition). Estimations : regarde tes relevés bancaires.
B15: Taux de droits de douane | C15: =IF(C8="UE",0,Paramètres!$C$10) -> 0 | D15: =IF(D8="UE",0,Paramètres!$C$10) -> 0 | E15: =IF(E8="UE",0,Paramètres!$C$10) -> 0 | F15: Repris des Paramètres. Sullab déclare une origine préférentielle Corée sur sa packing list, donc 0 % avec l'accord UE-Corée. Pour CNR et Shift, demande la même mention sur la facture.
B16: Droits de douane (€) | C16: =(C10+C11+C12)*C15 -> 0 | D16: =(D10+D11+D12)*D15 -> 0 | E16: =(E10+E11+E12)*E15 -> 0 | F16: Calculés sur marchandise + fret + assurance.
B17: TVA à l'import (€) | C17: =IF(C8="UE",0,(C10+C11+C12+C16)*Paramètres!$C$6) -> 705.64892 | D17: =IF(D8="UE",0,(D10+D11+D12+D16)*Paramètres!$C$6) -> 443.02 | E17: =IF(E8="UE",0,(E10+E11+E12+E16)*Paramètres!$C$6) -> 91.1 | F17: 20 % sur (marchandise + fret + assurance + droits). Récupérable si l'import est fait au nom de la SAS (voir Mode d'emploi).
B18: Total payé pour cette commande (€) | C18: =SUM(C10:C14)+C16+C17 -> 4288.8935 | D18: =SUM(D10:D14)+D16+D17 -> 2713.12 | E18: =SUM(E10:E14)+E16+E17 -> 586.6
B19: Coefficient d'approche hors TVA | C19: =IF(C10=0,1,(C18-C17)/C10) -> 1.2515961 | D19: =IF(D10=0,1,(D18-D17)/D10) -> 1.1552084 | E19: =IF(E10=0,1,(E18-E17)/E10) -> 1.1390805 | F19: Coût arrivé ÷ valeur de la marchandise, sans la TVA import.
B20: Coefficient d'approche TVA import comprise | C20: =IF(C10=0,1,C18/C10) -> 1.4980731 | D20: =IF(D10=0,1,D18/D10) -> 1.3806524 | E20: =IF(E10=0,1,E18/E10) -> 1.3485057 | F20: Idem en comptant la TVA import comme un coût.
B21: COEFFICIENT RETENU | C21: =IF((Paramètres!$C$5="Assujettie"),C19,C20) -> 1.2515961 | D21: =IF((Paramètres!$C$5="Assujettie"),D19,D20) -> 1.1552084 | E21: =IF((Paramètres!$C$5="Assujettie"),E19,E20) -> 1.1390805 | F21: Selon ton statut TVA. Il est appliqué à tous les prix de l'onglet de ce fournisseur.

Sheet Tarifs Onsha-Sullab
A1: Tarifs Sullab Co., Ltd. (Onsha / Sullab) · FOB Corée, en USD
A2: Sources : fiche « Onsha FOB Price USD » (Sullab Co., Ltd.), pro forma du 08/05/2026 (564 $), packing list SUL-0123 du 23/01/2026 (5 cartons, 33,5 kg, envoi par avion, origine préférentielle Corée). Paiement 50 % T/T à la commande, solde après expédition. Carton 55 × 34 × 19 cm, 60 cartons max par palette.
A4: Réf. | B4: Produit (fiche fournisseur) | C4: Correspondance Sunsoari | D4: Prix unitaire au carton (USD) | E4: Prix d'un carton (USD) | F4: Pièces par carton | G4: Prix unitaire MOQ (USD) | H4: Quantité MOQ (pcs) | I4: Total MOQ (USD) | J4: Prix public Corée (USD) | K4: Poids carton (kg) | L4: Remarques | M4: Prix retenu (USD) | N4: Coût d'achat (€) | O4: Coût de revient rendu (€)
A5: 1 | B5: Shower Head | C5: Douchette filtrante Onsha (« Shower Head (Travel) » sur la pro forma du 08/05/2026) | D5: 6.5 | E5: =D5*F5 -> 260 | F5: 40 | G5: 5.5 | H5: 1000 | I5: =G5*H5 -> 5500 | J5: 15.5 | K5: 7.5 | M5: =IF(Paramètres!$C$9="MOQ",G5,D5) -> 6.5 | N5: =M5*Paramètres!$C$7 -> 5.59 | O5: =N5*Import!$C$21 -> 6.9964223
A6: 2 | B6: Shower Head Cover | C6: Housse personnalisable pour douchette | D6: 3.7 | E6: =D6*F6 -> 185 | F6: 50 | G6: 3.2 | H6: 1000 | I6: =G6*H6 -> 3200 | J6: 6.54 | K6: 5.5 | M6: =IF(Paramètres!$C$9="MOQ",G6,D6) -> 3.7 | N6: =M6*Paramètres!$C$7 -> 3.182 | O6: =N6*Import!$C$21 -> 3.9825789
A7: 3 | B7: Shower Head Filter | C7: Filtres sédiment x3 (recharges douchette) | D7: 4.2 | E7: =D7*F7 -> 226.8 | F7: 54 | G7: 3.8 | H7: 1026 | I7: =G7*H7 -> 3898.8 | J7: 9.5 | K7: 6.5 | L7: 1 paquet = 3 filtres | M7: =IF(Paramètres!$C$9="MOQ",G7,D7) -> 4.2 | N7: =M7*Paramètres!$C$7 -> 3.612 | O7: =N7*Import!$C$21 -> 4.5207652
A8: 4 | B8: PVC Shower Tube 1.5 M | C8: Non vendu actuellement (flexible 1,5 m) | D8: 6 | E8: =D8*F8 -> 144 | F8: 24 | G8: 5 | H8: 1008 | I8: =G8*H8 -> 5040 | J8: 15 | K8: 8 | L8: Blanc, noir, gris, bleu, violet, rose | M8: =IF(Paramètres!$C$9="MOQ",G8,D8) -> 6 | N8: =M8*Paramètres!$C$7 -> 5.16 | O8: =N8*Import!$C$21 -> 6.458236
A9: 5 | B9: PVC Shower Tube 2.0 M | C9: Non vendu actuellement (flexible 2 m) | D9: 6.5 | E9: =D9*F9 -> 156 | F9: 24 | G9: 5.2 | H9: 1008 | I9: =G9*H9 -> 5241.6 | J9: 16 | K9: 9 | L9: Blanc, noir, gris, bleu, violet, rose | M9: =IF(Paramètres!$C$9="MOQ",G9,D9) -> 6.5 | N9: =M9*Paramètres!$C$7 -> 5.59 | O9: =N9*Import!$C$21 -> 6.9964223
A10: 6 | B10: Hot-Spring Filter Set (Mini) | C10: Set Découverte Nomade (coque + 4 capsules) | D10: 10.2 | E10: =D10*F10 -> 183.6 | F10: 18 | G10: 9.2 | H10: 1008 | I10: =G10*H10 -> 9273.6 | J10: 29 | K10: 5 | M10: =IF(Paramètres!$C$9="MOQ",G10,D10) -> 10.2 | N10: =M10*Paramètres!$C$7 -> 8.772 | O10: =N10*Import!$C$21 -> 10.979001
A11: 7 | B11: Hot-Spring Refill Filter: Wood | C11: Capsule thermale Nomade · Hinoki | D11: 2.3 | E11: =D11*F11 -> 460 | F11: 200 | G11: 1.8 | H11: 1000 | I11: =G11*H11 -> 1800 | J11: 6.54 | K11: 5.5 | M11: =IF(Paramètres!$C$9="MOQ",G11,D11) -> 2.3 | N11: =M11*Paramètres!$C$7 -> 1.978 | O11: =N11*Import!$C$21 -> 2.4756571
A12: 8 | B12: Hot-Spring Refill Filter: Ocean | C12: Capsule thermale Nomade · Océan | D12: 2.3 | E12: =D12*F12 -> 460 | F12: 200 | G12: 1.8 | H12: 1000 | I12: =G12*H12 -> 1800 | J12: 6.54 | K12: 5.5 | M12: =IF(Paramètres!$C$9="MOQ",G12,D12) -> 2.3 | N12: =M12*Paramètres!$C$7 -> 1.978 | O12: =N12*Import!$C$21 -> 2.4756571
A13: 9 | B13: Hot-Spring Refill Filter: Pine Tree | C13: Capsule thermale Nomade · Forêt de Pin | D13: 2.3 | E13: =D13*F13 -> 460 | F13: 200 | G13: 1.8 | H13: 1000 | I13: =G13*H13 -> 1800 | J13: 6.54 | K13: 5.5 | M13: =IF(Paramètres!$C$9="MOQ",G13,D13) -> 2.3 | N13: =M13*Paramètres!$C$7 -> 1.978 | O13: =N13*Import!$C$21 -> 2.4756571
A14: 10 | B14: Hot-Spring Refill Filter: Flower | C14: Capsule thermale Nomade · Fleur de Prunier | D14: 2.3 | E14: =D14*F14 -> 460 | F14: 200 | G14: 1.8 | H14: 1000 | I14: =G14*H14 -> 1800 | J14: 6.54 | K14: 5.5 | M14: =IF(Paramètres!$C$9="MOQ",G14,D14) -> 2.3 | N14: =M14*Paramètres!$C$7 -> 1.978 | O14: =N14*Import!$C$21 -> 2.4756571
A15: 11 | B15: Hot-Spring Filter case (Mini) | C15: Coque de diffusion Nomade | D15: 2.3 | E15: =D15*F15 -> 460 | F15: 200 | G15: 1.8 | H15: 1000 | I15: =G15*H15 -> 1800 | J15: 6.15 | K15: 10.5 | M15: =IF(Paramètres!$C$9="MOQ",G15,D15) -> 2.3 | N15: =M15*Paramètres!$C$7 -> 1.978 | O15: =N15*Import!$C$21 -> 2.4756571
A16: 12 | B16: Compact Shower Head | C16: Pommeau de douche filtrant Onsha (pro forma du 08/05/2026 : 70 pcs à 6,20 $) | D16: 6.2 | E16: =D16*F16 -> 260.4 | F16: 42 | G16: 5.2 | H16: 1008 | I16: =G16*H16 -> 5241.6 | J16: 12.5 | K16: 8.5 | M16: =IF(Paramètres!$C$9="MOQ",G16,D16) -> 6.2 | N16: =M16*Paramètres!$C$7 -> 5.332 | O16: =N16*Import!$C$21 -> 6.6735105
A17: 13 | B17: Hot-Spring Filter Set (Home) | C17: Set Découverte Home (coque + 4 filtres) | D17: 20 | E17: =D17*F17 -> 240 | F17: 12 | G17: 18.5 | H17: 1008 | I17: =G17*H17 -> 18648 | J17: 45 | K17: 6.5 | M17: =IF(Paramètres!$C$9="MOQ",G17,D17) -> 20 | N17: =M17*Paramètres!$C$7 -> 17.2 | O17: =N17*Import!$C$21 -> 21.527453
A18: 14 | B18: Hot-Spring Refill Filter: Wood (Home) | C18: Filtre thermal Home · Hinoki | D18: 4.7 | E18: =D18*F18 -> 338.4 | F18: 72 | G18: 4.2 | H18: 1008 | I18: =G18*H18 -> 4233.6 | J18: 11 | K18: 6.5 | M18: =IF(Paramètres!$C$9="MOQ",G18,D18) -> 4.7 | N18: =M18*Paramètres!$C$7 -> 4.042 | O18: =N18*Import!$C$21 -> 5.0589515
A19: 15 | B19: Hot-Spring Refill Filter: Ocean (Home) | C19: Filtre thermal Home · Océan | D19: 4.7 | E19: =D19*F19 -> 338.4 | F19: 72 | G19: 4.2 | H19: 1008 | I19: =G19*H19 -> 4233.6 | J19: 11 | K19: 6.5 | M19: =IF(Paramètres!$C$9="MOQ",G19,D19) -> 4.7 | N19: =M19*Paramètres!$C$7 -> 4.042 | O19: =N19*Import!$C$21 -> 5.0589515
A20: 16 | B20: Hot-Spring Refill Filter: Pine Tree (Home) | C20: Filtre thermal Home · Forêt de Pin | D20: 4.7 | E20: =D20*F20 -> 338.4 | F20: 72 | G20: 4.2 | H20: 1008 | I20: =G20*H20 -> 4233.6 | J20: 11 | K20: 6.5 | M20: =IF(Paramètres!$C$9="MOQ",G20,D20) -> 4.7 | N20: =M20*Paramètres!$C$7 -> 4.042 | O20: =N20*Import!$C$21 -> 5.0589515
A21: 17 | B21: Hot-Spring Refill Filter: Flower (Home) | C21: Filtre thermal Home · Fleur de Prunier | D21: 4.7 | E21: =D21*F21 -> 338.4 | F21: 72 | G21: 4.2 | H21: 1008 | I21: =G21*H21 -> 4233.6 | J21: 11 | K21: 6.5 | M21: =IF(Paramètres!$C$9="MOQ",G21,D21) -> 4.7 | N21: =M21*Paramètres!$C$7 -> 4.042 | O21: =N21*Import!$C$21 -> 5.0589515
A22: 18 | B22: Hot-Spring Filter case (HOME) | C22: Coque de diffusion Home (« Filter Case (Home) » sur la packing list) | D22: 2.3 | E22: =D22*F22 -> 165.6 | F22: 72 | G22: 1.8 | H22: 1008 | I22: =G22*H22 -> 1814.4 | J22: 9 | K22: 8.5 | M22: =IF(Paramètres!$C$9="MOQ",G22,D22) -> 2.3 | N22: =M22*Paramètres!$C$7 -> 1.978 | O22: =N22*Import!$C$21 -> 2.4756571
A23: 19 | B23: Faucet Filter with case (HOME) | C23: Sullab · Filtre robinet lavabo | D23: 5.4 | E23: =D23*F23 -> 388.8 | F23: 72 | G23: 4.6 | H23: 1008 | I23: =G23*H23 -> 4636.8 | J23: 15 | K23: 9 | L23: 6 adaptateurs et outil inclus | M23: =IF(Paramètres!$C$9="MOQ",G23,D23) -> 5.4 | N23: =M23*Paramètres!$C$7 -> 4.644 | O23: =N23*Import!$C$21 -> 5.8124124
A24: 20 | B24: Hot-Spring Filter case (HOME) · paquet de 3 | C24: Sullab · Lot 3 sédiments robinet (« Faucet Filter Refill (Home) » sur la packing list) | D24: 2.3 | E24: =D24*F24 -> 487.6 | F24: 212 | G24: 1.9 | H24: 1060 | I24: =G24*H24 -> 2014 | J24: 9 | K24: 8.5 | L24: 1 paquet = 3 filtres | M24: =IF(Paramètres!$C$9="MOQ",G24,D24) -> 2.3 | N24: =M24*Paramètres!$C$7 -> 1.978 | O24: =N24*Import!$C$21 -> 2.4756571

Sheet Tarifs Shift
A1: Tarifs SHIFT (Heraldsilver Inc.) · FOB Corée (Incheon), en USD
A2: Source : « SHIFT wholesale price Order Sheet 260528 ». Paiement 100 % avant expédition. Ta commande sur cette fiche : 230 pièces pour 2 285 $.
A4: Réf. | B4: Produit (fiche fournisseur) | C4: Utilisé dans (Sunsoari) | D4: Prix fournisseur | E4: Devise | F4: Pièces par carton | G4: Prix public Corée (KRW) | H4: Code douanier | I4: Ta commande (pcs) | J4: Taux de change | K4: Coût d'achat (€) | L4: Coût de revient rendu (€)
A5: S1 | B5: Capsule Shower Head (+ 1 filtre sédiment) | C5: Coffret Soin (avec 1 capsule) | D5: 14.5 | E5: USD | F5: 26 | G5: 51000 | H5: 8421.21 / 3924.90 | I5: 0 | J5: =IF(E5="USD",Paramètres!$C$7,IF(E5="KRW",Paramètres!$C$8,1)) -> 0.86 | K5: =D5*J5 -> 12.47 | L5: =K5*Import!$D$21 -> 14.405449
A6: S2 | B6: Capsule Shower Trial Kit (pommeau + 1 filtre + 3 capsules) | C6: Non relié pour l'instant (voir remarque) | D6: 18.5 | E6: USD | F6: 8 | G6: 59600 | H6: 8421.21 | I6: 70 | J6: =IF(E6="USD",Paramètres!$C$7,IF(E6="KRW",Paramètres!$C$8,1)) -> 0.86 | K6: =D6*J6 -> 15.91 | L6: =K6*Import!$D$21 -> 18.379365
A7: S3 | B7: Aroma Therapy Shower Kit (pommeau + 3 filtres + flexible 2 m + 6 capsules) | C7: Coffret Douche & Aromathérapie | D7: 35 | E7: USD | F7: 4 | G7: 122000 | H7: non indiqué | I7: 0 | J7: =IF(E7="USD",Paramètres!$C$7,IF(E7="KRW",Paramètres!$C$8,1)) -> 0.86 | K7: =D7*J7 -> 30.1 | L7: =K7*Import!$D$21 -> 34.771772
A8: S4 | B8: Aroma Capsule, boîte de 6 | C8: Pack 6 capsules, coffrets | D8: 6.5 | E8: USD | F8: 20 | G8: 23400 | H8: 3307.30 | I8: 130 | J8: =IF(E8="USD",Paramètres!$C$7,IF(E8="KRW",Paramètres!$C$8,1)) -> 0.86 | K8: =D8*J8 -> 5.59 | L8: =K8*Import!$D$21 -> 6.4576149
A9: S5 | B9: Vitamin Capsule Shower filter (sédiment), boîte de 3 | C9: Pack 3 filtres | D9: 5.5 | E9: USD | F9: 120 | G9: 17700 | H9: 8421.99 | I9: 50 | J9: =IF(E9="USD",Paramètres!$C$7,IF(E9="KRW",Paramètres!$C$8,1)) -> 0.86 | K9: =D9*J9 -> 4.73 | L9: =K9*Import!$D$21 -> 5.4641357
A10: S6 | B10: Silicone Self-draining shower hose 1,5 m ou 2 m | C10: Non vendu seul pour l'instant | D10: 13 | E10: USD | F10: 14 | G10: 33000 | H10: 8421.21 | I10: 0 | J10: =IF(E10="USD",Paramètres!$C$7,IF(E10="KRW",Paramètres!$C$8,1)) -> 0.86 | K10: =D10*J10 -> 11.18 | L10: =K10*Import!$D$21 -> 12.91523
A12: Remarque : sur ta commande, tu as pris 70 Trial Kits (blanc 30, noir 20, rose 10, vert 10) et aucun Aroma Kit complet. Si ton « Coffret Douche & Aromathérapie » est composé à partir des Trial Kits, dis-le-moi et je change la composition.
A13: Une note de 11,44 apparaît à côté des flexibles sur la fiche : s'il s'agit d'un prix négocié, remplace 13 par 11,44.
A14: Capsules (code 3307.30) : ce sont des préparations pour le bain, donc des produits cosmétiques. La colonne CPNP de la fiche est vide pour elles : demande à SHIFT le numéro de notification CPNP et qui est la personne responsable dans l'UE.

Sheet Autres fournisseurs
A1: CNR Cosmetics Co., Ltd. · facture C-2026-0915 du 15/09/2026 · prix en EUR, DAP
A2: DAP = livraison payée jusque chez toi par le fournisseur, mais droits et TVA à l'import restent à ta charge. Payé 500 $ (facture n° 0019 du 16/09/2026). Produits pas encore sur Shopify.
A4: Produit | B4: Quantité | C4: Prix unitaire (€) | D4: Montant (€) | E4: Coût de revient rendu unitaire (€) | F4: Prix de vente TTC prévu (€) | G4: Coefficient | H4: Remarque
A5: 104 Multi Boosting Serum | B5: 7 | C5: 15 | D5: =B5*C5 -> 105 | E5: =C5*Import!$E$21 -> 17.086207 | G5: =IF(OR(E5=0,F5=""),0,F5/E5) -> 0
A6: 104 Multi Boosting Serum Refill | B6: 10 | C6: 10 | D6: =B6*C6 -> 100 | E6: =C6*Import!$E$21 -> 11.390805 | G6: =IF(OR(E6=0,F6=""),0,F6/E6) -> 0
A7: Nonstick Sunstick | B7: 5 | C7: 10 | D7: =B7*C7 -> 50 | E7: =C7*Import!$E$21 -> 11.390805 | G7: =IF(OR(E7=0,F7=""),0,F7/E7) -> 0
A8: MOJU Sensitive C Cleanser | B8: 5 | C8: 10 | D8: =B8*C8 -> 50 | E8: =C8*Import!$E$21 -> 11.390805 | G8: =IF(OR(E8=0,F8=""),0,F8/E8) -> 0
A9: MOJU Mask Pack | B9: 10 | C9: 5 | D9: =B9*C9 -> 50 | E9: =C9*Import!$E$21 -> 5.6954023 | G9: =IF(OR(E9=0,F9=""),0,F9/E9) -> 0 | H9: Mini format : idéal en cadeau ou échantillon.
A10: 104 One Cream Travel Size | B10: 10 | C10: 4 | D10: =B10*C10 -> 40 | E10: =C10*Import!$E$21 -> 4.5563218 | G10: =IF(OR(E10=0,F10=""),0,F10/E10) -> 0 | H10: Mini format : idéal en cadeau ou échantillon.
A11: 104 Multi Boosting Serum Travel Size | B11: 10 | C11: 4 | D11: =B11*C11 -> 40 | E11: =C11*Import!$E$21 -> 4.5563218 | G11: =IF(OR(E11=0,F11=""),0,F11/E11) -> 0 | H11: Mini format : idéal en cadeau ou échantillon.
A12: Total marchandise | D12: =SUM(D5:D11) -> 435
A13: Transport facturé 150 € − prise en charge THE C 129,5 € | D13: 20.5
A14: Total facture | D14: =D12+D13 -> 455.5
A16: ⚠ Cosmétiques : avant de les vendre, il faut une personne responsable établie dans l'UE, une notification CPNP, un étiquetage en français et un dossier information produit (DIP). Si personne d'autre ne l'assure, c'est Sunsoari, en tant qu'importateur, qui en a la charge. Vérifie ce point avec CNR avant la mise en vente.

Sheet Marges produits
A1: Marge par produit Sunsoari
A2: Prix de vente repris de Shopify le 11/10/2026 (modifiables en bleu). La colonne « Composition » explique quelles références fournisseur forment chaque produit.
A4: Marque | B4: Produit Shopify | C4: SKU | D4: Composition (réf. fournisseur) | E4: Prix de vente TTC (€) | F4: Coût d'achat fournisseur (€) | G4: Coût de revient rendu (€) | H4: CA encaissé (€) | I4: Frais de paiement % (€) | J4: Cotisations (€) | K4: Marge produit (€) | L4: Taux de marge (% du CA) | M4: Coefficient (prix TTC ÷ coût) | N4: Marge si commande de cet article seul, après colis, emballage, cadeau et livraison facturée (€) | O4: Prix plancher au coefficient visé (€) | P4: Alerte
A5: Onsha | B5: Pommeau de Douche Filtrant | C5: ONSHA-POMMEAU | D5: Réf. 12 | E5: 23.9 | F5: ='Tarifs Onsha-Sullab'!$N$16 -> 5.332 | G5: ='Tarifs Onsha-Sullab'!$O$16 -> 6.6735105 | H5: =IF((Paramètres!$C$5="Assujettie"),E5/(1+Paramètres!$C$6),E5) -> 19.916667 | I5: =E5*Paramètres!$C$11 -> 0.3585 | J5: =H5*Paramètres!$C$13 -> 0 | K5: =IF(G5=0,0,H5-G5-I5-J5) -> 12.884656 | L5: =IF(H5=0,0,K5/H5) -> 0.64692834 | M5: =IF(G5=0,0,E5/G5) -> 3.5813235 | N5: =IF(G5=0,0,K5-Paramètres!$C$12-(Paramètres!$C$14+Paramètres!$C$22+Paramètres!$C$23)*IF((Paramètres!$C$5="Assujettie"),1/(1+Paramètres!$C$6),1)-Paramètres!$C$24+IF(E5>=Paramètres!$C$16,0,Paramètres!$C$15*IF((Paramètres!$C$5="Assujettie"),1/(1+Paramètres!$C$6),1)*(1-Paramètres!$C$13)-Paramètres!$C$15*Paramètres!$C$11)) -> 12.462823 | O5: =G5*Paramètres!$C$25 -> 20.020532 | P5: =IF(G5=0,"Prix fournisseur manquant",IF(N5<0,"Perte si vendu seul",IF(L5<Paramètres!$C$26,"Marge faible","OK"))) -> OK
A6: Onsha | B6: Douchette Filtrante | C6: ONSHA-DOUCHETTE | D6: Réf. 1 | E6: 23.9 | F6: ='Tarifs Onsha-Sullab'!$N$5 -> 5.59 | G6: ='Tarifs Onsha-Sullab'!$O$5 -> 6.9964223 | H6: =IF((Paramètres!$C$5="Assujettie"),E6/(1+Paramètres!$C$6),E6) -> 19.916667 | I6: =E6*Paramètres!$C$11 -> 0.3585 | J6: =H6*Paramètres!$C$13 -> 0 | K6: =IF(G6=0,0,H6-G6-I6-J6) -> 12.561744 | L6: =IF(H6=0,0,K6/H6) -> 0.6307152 | M6: =IF(G6=0,0,E6/G6) -> 3.4160316 | N6: =IF(G6=0,0,K6-Paramètres!$C$12-(Paramètres!$C$14+Paramètres!$C$22+Paramètres!$C$23)*IF((Paramètres!$C$5="Assujettie"),1/(1+Paramètres!$C$6),1)-Paramètres!$C$24+IF(E6>=Paramètres!$C$16,0,Paramètres!$C$15*IF((Paramètres!$C$5="Assujettie"),1/(1+Paramètres!$C$6),1)*(1-Paramètres!$C$13)-Paramètres!$C$15*Paramètres!$C$11)) -> 12.139911 | O6: =G6*Paramètres!$C$25 -> 20.989267 | P6: =IF(G6=0,"Prix fournisseur manquant",IF(N6<0,"Perte si vendu seul",IF(L6<Paramètres!$C$26,"Marge faible","OK"))) -> OK
A7: Onsha | B7: Filtres Sédiment x3 (recharges douchette) | C7: ONSHA-SEDIMENT | D7: Réf. 3 (paquet de 3) | E7: 13.9 | F7: ='Tarifs Onsha-Sullab'!$N$7 -> 3.612 | G7: ='Tarifs Onsha-Sullab'!$O$7 -> 4.5207652 | H7: =IF((Paramètres!$C$5="Assujettie"),E7/(1+Paramètres!$C$6),E7) -> 11.583333 | I7: =E7*Paramètres!$C$11 -> 0.2085 | J7: =H7*Paramètres!$C$13 -> 0 | K7: =IF(G7=0,0,H7-G7-I7-J7) -> 6.8540681 | L7: =IF(H7=0,0,K7/H7) -> 0.59171811 | M7: =IF(G7=0,0,E7/G7) -> 3.0747007 | N7: =IF(G7=0,0,K7-Paramètres!$C$12-(Paramètres!$C$14+Paramètres!$C$22+Paramètres!$C$23)*IF((Paramètres!$C$5="Assujettie"),1/(1+Paramètres!$C$6),1)-Paramètres!$C$24+IF(E7>=Paramètres!$C$16,0,Paramètres!$C$15*IF((Paramètres!$C$5="Assujettie"),1/(1+Paramètres!$C$6),1)*(1-Paramètres!$C$13)-Paramètres!$C$15*Paramètres!$C$11)) -> 6.4322348 | O7: =G7*Paramètres!$C$25 -> 13.562296 | P7: =IF(G7=0,"Prix fournisseur manquant",IF(N7<0,"Perte si vendu seul",IF(L7<Paramètres!$C$26,"Marge faible","OK"))) -> OK
A8: Onsha | B8: Housse Personnalisable pour Douchette | C8: ONSHA-HOUSSE-* | D8: Réf. 2 | E8: 9.9 | F8: ='Tarifs Onsha-Sullab'!$N$6 -> 3.182 | G8: ='Tarifs Onsha-Sullab'!$O$6 -> 3.9825789 | H8: =IF((Paramètres!$C$5="Assujettie"),E8/(1+Paramètres!$C$6),E8) -> 8.25 | I8: =E8*Paramètres!$C$11 -> 0.1485 | J8: =H8*Paramètres!$C$13 -> 0 | K8: =IF(G8=0,0,H8-G8-I8-J8) -> 4.1189211 | L8: =IF(H8=0,0,K8/H8) -> 0.49926317 | M8: =IF(G8=0,0,E8/G8) -> 2.4858265 | N8: =IF(G8=0,0,K8-Paramètres!$C$12-(Paramètres!$C$14+Paramètres!$C$22+Paramètres!$C$23)*IF((Paramètres!$C$5="Assujettie"),1/(1+Paramètres!$C$6),1)-Paramètres!$C$24+IF(E8>=Paramètres!$C$16,0,Paramètres!$C$15*IF((Paramètres!$C$5="Assujettie"),1/(1+Paramètres!$C$6),1)*(1-Paramètres!$C$13)-Paramètres!$C$15*Paramètres!$C$11)) -> 3.6970878 | O8: =G8*Paramètres!$C$25 -> 11.947737 | P8: =IF(G8=0,"Prix fournisseur manquant",IF(N8<0,"Perte si vendu seul",IF(L8<Paramètres!$C$26,"Marge faible","OK"))) -> OK
A9: Onsha | B9: Coque de Diffusion Home | C9: ONSHA-COQUE-HOME | D9: Réf. 18 | E9: 19.9 | F9: ='Tarifs Onsha-Sullab'!$N$22 -> 1.978 | G9: ='Tarifs Onsha-Sullab'!$O$22 -> 2.4756571 | H9: =IF((Paramètres!$C$5="Assujettie"),E9/(1+Paramètres!$C$6),E9) -> 16.583333 | I9: =E9*Paramètres!$C$11 -> 0.2985 | J9: =H9*Paramètres!$C$13 -> 0 | K9: =IF(G9=0,0,H9-G9-I9-J9) -> 13.809176 | L9: =IF(H9=0,0,K9/H9) -> 0.83271414 | M9: =IF(G9=0,0,E9/G9) -> 8.0382698 | N9: =IF(G9=0,0,K9-Paramètres!$C$12-(Paramètres!$C$14+Paramètres!$C$22+Paramètres!$C$23)*IF((Paramètres!$C$5="Assujettie"),1/(1+Paramètres!$C$6),1)-Paramètres!$C$24+IF(E9>=Paramètres!$C$16,0,Paramètres!$C$15*IF((Paramètres!$C$5="Assujettie"),1/(1+Paramètres!$C$6),1)*(1-Paramètres!$C$13)-Paramètres!$C$15*Paramètres!$C$11)) -> 13.387343 | O9: =G9*Paramètres!$C$25 -> 7.4269714 | P9: =IF(G9=0,"Prix fournisseur manquant",IF(N9<0,"Perte si vendu seul",IF(L9<Paramètres!$C$26,"Marge faible","OK"))) -> OK
A10: Onsha | B10: Coque de Diffusion Nomade | C10: ONSHA-COQUE-NOMADE | D10: Réf. 11 | E10: 9.9 | F10: ='Tarifs Onsha-Sullab'!$N$15 -> 1.978 | G10: ='Tarifs Onsha-Sullab'!$O$15 -> 2.4756571 | H10: =IF((Paramètres!$C$5="Assujettie"),E10/(1+Paramètres!$C$6),E10) -> 8.25 | I10: =E10*Paramètres!$C$11 -> 0.1485 | J10: =H10*Paramètres!$C$13 -> 0 | K10: =IF(G10=0,0,H10-G10-I10-J10) -> 5.6258429 | L10: =IF(H10=0,0,K10/H10) -> 0.68192035 | M10: =IF(G10=0,0,E10/G10) -> 3.9989383 | N10: =IF(G10=0,0,K10-Paramètres!$C$12-(Paramètres!$C$14+Paramètres!$C$22+Paramètres!$C$23)*IF((Paramètres!$C$5="Assujettie"),1/(1+Paramètres!$C$6),1)-Paramètres!$C$24+IF(E10>=Paramètres!$C$16,0,Paramètres!$C$15*IF((Paramètres!$C$5="Assujettie"),1/(1+Paramètres!$C$6),1)*(1-Paramètres!$C$13)-Paramètres!$C$15*Paramètres!$C$11)) -> 5.2040095 | O10: =G10*Paramètres!$C$25 -> 7.4269714 | P10: =IF(G10=0,"Prix fournisseur manquant",IF(N10<0,"Perte si vendu seul",IF(L10<Paramètres!$C$26,"Marge faible","OK"))) -> OK
A11: Onsha | B11: Filtre Thermal Vitaminé (Home) | C11: ONSHA-FILTRE-* | D11: Réf. 14 à 17 | E11: 12.9 | F11: ='Tarifs Onsha-Sullab'!$N$18 -> 4.042 | G11: ='Tarifs Onsha-Sullab'!$O$18 -> 5.0589515 | H11: =IF((Paramètres!$C$5="Assujettie"),E11/(1+Paramètres!$C$6),E11) -> 10.75 | I11: =E11*Paramètres!$C$11 -> 0.1935 | J11: =H11*Paramètres!$C$13 -> 0 | K11: =IF(G11=0,0,H11-G11-I11-J11) -> 5.4975485 | L11: =IF(H11=0,0,K11/H11) -> 0.51139986 | M11: =IF(G11=0,0,E11/G11) -> 2.5499355 | N11: =IF(G11=0,0,K11-Paramètres!$C$12-(Paramètres!$C$14+Paramètres!$C$22+Paramètres!$C$23)*IF((Paramètres!$C$5="Assujettie"),1/(1+Paramètres!$C$6),1)-Paramètres!$C$24+IF(E11>=Paramètres!$C$16,0,Paramètres!$C$15*IF((Paramètres!$C$5="Assujettie"),1/(1+Paramètres!$C$6),1)*(1-Paramètres!$C$13)-Paramètres!$C$15*Paramètres!$C$11)) -> 5.0757151 | O11: =G11*Paramètres!$C$25 -> 15.176855 | P11: =IF(G11=0,"Prix fournisseur manquant",IF(N11<0,"Perte si vendu seul",IF(L11<Paramètres!$C$26,"Marge faible","OK"))) -> OK
A12: Onsha | B12: Filtre Thermal Vitaminé (Home) Sans Senteur | C12: ONSHA-FILTRE-SANS-X1 | D12: Absent de la fiche : même prix que réf. 14 supposé | E12: 12.9 | F12: ='Tarifs Onsha-Sullab'!$N$18 -> 4.042 | G12: ='Tarifs Onsha-Sullab'!$O$18 -> 5.0589515 | H12: =IF((Paramètres!$C$5="Assujettie"),E12/(1+Paramètres!$C$6),E12) -> 10.75 | I12: =E12*Paramètres!$C$11 -> 0.1935 | J12: =H12*Paramètres!$C$13 -> 0 | K12: =IF(G12=0,0,H12-G12-I12-J12) -> 5.4975485 | L12: =IF(H12=0,0,K12/H12) -> 0.51139986 | M12: =IF(G12=0,0,E12/G12) -> 2.5499355 | N12: =IF(G12=0,0,K12-Paramètres!$C$12-(Paramètres!$C$14+Paramètres!$C$22+Paramètres!$C$23)*IF((Paramètres!$C$5="Assujettie"),1/(1+Paramètres!$C$6),1)-Paramètres!$C$24+IF(E12>=Paramètres!$C$16,0,Paramètres!$C$15*IF((Paramètres!$C$5="Assujettie"),1/(1+Paramètres!$C$6),1)*(1-Paramètres!$C$13)-Paramètres!$C$15*Paramètres!$C$11)) -> 5.0757151 | O12: =G12*Paramètres!$C$25 -> 15.176855 | P12: =IF(G12=0,"Prix fournisseur manquant",IF(N12<0,"Perte si vendu seul",IF(L12<Paramètres!$C$26,"Marge faible","OK"))) -> OK
A13: Onsha | B13: Capsule Thermale Coréenne (Nomade) | C13: ONSHA-CAPSULE-* | D13: Réf. 7 à 10 | E13: 6.9 | F13: ='Tarifs Onsha-Sullab'!$N$11 -> 1.978 | G13: ='Tarifs Onsha-Sullab'!$O$11 -> 2.4756571 | H13: =IF((Paramètres!$C$5="Assujettie"),E13/(1+Paramètres!$C$6),E13) -> 5.75 | I13: =E13*Paramètres!$C$11 -> 0.1035 | J13: =H13*Paramètres!$C$13 -> 0 | K13: =IF(G13=0,0,H13-G13-I13-J13) -> 3.1708429 | L13: =IF(H13=0,0,K13/H13) -> 0.55145093 | M13: =IF(G13=0,0,E13/G13) -> 2.7871388 | N13: =IF(G13=0,0,K13-Paramètres!$C$12-(Paramètres!$C$14+Paramètres!$C$22+Paramètres!$C$23)*IF((Paramètres!$C$5="Assujettie"),1/(1+Paramètres!$C$6),1)-Paramètres!$C$24+IF(E13>=Paramètres!$C$16,0,Paramètres!$C$15*IF((Paramètres!$C$5="Assujettie"),1/(1+Paramètres!$C$6),1)*(1-Paramètres!$C$13)-Paramètres!$C$15*Paramètres!$C$11)) -> 2.7490095 | O13: =G13*Paramètres!$C$25 -> 7.4269714 | P13: =IF(G13=0,"Prix fournisseur manquant",IF(N13<0,"Perte si vendu seul",IF(L13<Paramètres!$C$26,"Marge faible","OK"))) -> OK
A14: Onsha | B14: Premier Rituel (Home) | C14: ONSHA-PREMIER-* | D14: Coque Home (18) + 1 filtre Home (14) | E14: 29.9 | F14: ='Tarifs Onsha-Sullab'!$N$22+'Tarifs Onsha-Sullab'!$N$18 -> 6.02 | G14: ='Tarifs Onsha-Sullab'!$O$22+'Tarifs Onsha-Sullab'!$O$18 -> 7.5346087 | H14: =IF((Paramètres!$C$5="Assujettie"),E14/(1+Paramètres!$C$6),E14) -> 24.916667 | I14: =E14*Paramètres!$C$11 -> 0.4485 | J14: =H14*Paramètres!$C$13 -> 0 | K14: =IF(G14=0,0,H14-G14-I14-J14) -> 16.933558 | L14: =IF(H14=0,0,K14/H14) -> 0.67960768 | M14: =IF(G14=0,0,E14/G14) -> 3.9683547 | N14: =IF(G14=0,0,K14-Paramètres!$C$12-(Paramètres!$C$14+Paramètres!$C$22+Paramètres!$C$23)*IF((Paramètres!$C$5="Assujettie"),1/(1+Paramètres!$C$6),1)-Paramètres!$C$24+IF(E14>=Paramètres!$C$16,0,Paramètres!$C$15*IF((Paramètres!$C$5="Assujettie"),1/(1+Paramètres!$C$6),1)*(1-Paramètres!$C$13)-Paramètres!$C$15*Paramètres!$C$11)) -> 16.511725 | O14: =G14*Paramètres!$C$25 -> 22.603826 | P14: =IF(G14=0,"Prix fournisseur manquant",IF(N14<0,"Perte si vendu seul",IF(L14<Paramètres!$C$26,"Marge faible","OK"))) -> OK
A15: Onsha | B15: Starter Home | C15: ONSHA-STARTER-* | D15: Pommeau (12) + coque Home (18) + 1 filtre Home (14) | E15: 49.9 | F15: ='Tarifs Onsha-Sullab'!$N$16+'Tarifs Onsha-Sullab'!$N$22+'Tarifs Onsha-Sullab'!$N$18 -> 11.352 | G15: ='Tarifs Onsha-Sullab'!$O$16+'Tarifs Onsha-Sullab'!$O$22+'Tarifs Onsha-Sullab'!$O$18 -> 14.208119 | H15: =IF((Paramètres!$C$5="Assujettie"),E15/(1+Paramètres!$C$6),E15) -> 41.583333 | I15: =E15*Paramètres!$C$11 -> 0.7485 | J15: =H15*Paramètres!$C$13 -> 0 | K15: =IF(G15=0,0,H15-G15-I15-J15) -> 26.626714 | L15: =IF(H15=0,0,K15/H15) -> 0.64032178 | M15: =IF(G15=0,0,E15/G15) -> 3.5120764 | N15: =IF(G15=0,0,K15-Paramètres!$C$12-(Paramètres!$C$14+Paramètres!$C$22+Paramètres!$C$23)*IF((Paramètres!$C$5="Assujettie"),1/(1+Paramètres!$C$6),1)-Paramètres!$C$24+IF(E15>=Paramètres!$C$16,0,Paramètres!$C$15*IF((Paramètres!$C$5="Assujettie"),1/(1+Paramètres!$C$6),1)*(1-Paramètres!$C$13)-Paramètres!$C$15*Paramètres!$C$11)) -> 26.204881 | O15: =G15*Paramètres!$C$25 -> 42.624358 | P15: =IF(G15=0,"Prix fournisseur manquant",IF(N15<0,"Perte si vendu seul",IF(L15<Paramètres!$C$26,"Marge faible","OK"))) -> OK
A16: Onsha | B16: Set Découverte Home | C16: ONSHA-SET-HOME | D16: Réf. 13 (set coque + 4 filtres) | E16: 59.9 | F16: ='Tarifs Onsha-Sullab'!$N$17 -> 17.2 | G16: ='Tarifs Onsha-Sullab'!$O$17 -> 21.527453 | H16: =IF((Paramètres!$C$5="Assujettie"),E16/(1+Paramètres!$C$6),E16) -> 49.916667 | I16: =E16*Paramètres!$C$11 -> 0.8985 | J16: =H16*Paramètres!$C$13 -> 0 | K16: =IF(G16=0,0,H16-G16-I16-J16) -> 27.490713 | L16: =IF(H16=0,0,K16/H16) -> 0.55073215 | M16: =IF(G16=0,0,E16/G16) -> 2.7824936 | N16: =IF(G16=0,0,K16-Paramètres!$C$12-(Paramètres!$C$14+Paramètres!$C$22+Paramètres!$C$23)*IF((Paramètres!$C$5="Assujettie"),1/(1+Paramètres!$C$6),1)-Paramètres!$C$24+IF(E16>=Paramètres!$C$16,0,Paramètres!$C$15*IF((Paramètres!$C$5="Assujettie"),1/(1+Paramètres!$C$6),1)*(1-Paramètres!$C$13)-Paramètres!$C$15*Paramètres!$C$11)) -> 27.06888 | O16: =G16*Paramètres!$C$25 -> 64.58236 | P16: =IF(G16=0,"Prix fournisseur manquant",IF(N16<0,"Perte si vendu seul",IF(L16<Paramètres!$C$26,"Marge faible","OK"))) -> OK
A17: Onsha | B17: Set Découverte Nomade | C17: ONSHA-SET-NOMADE | D17: Réf. 6 (set coque + 4 capsules) | E17: 29.9 | F17: ='Tarifs Onsha-Sullab'!$N$10 -> 8.772 | G17: ='Tarifs Onsha-Sullab'!$O$10 -> 10.979001 | H17: =IF((Paramètres!$C$5="Assujettie"),E17/(1+Paramètres!$C$6),E17) -> 24.916667 | I17: =E17*Paramètres!$C$11 -> 0.4485 | J17: =H17*Paramètres!$C$13 -> 0 | K17: =IF(G17=0,0,H17-G17-I17-J17) -> 13.489165 | L17: =IF(H17=0,0,K17/H17) -> 0.54137119 | M17: =IF(G17=0,0,E17/G17) -> 2.7233807 | N17: =IF(G17=0,0,K17-Paramètres!$C$12-(Paramètres!$C$14+Paramètres!$C$22+Paramètres!$C$23)*IF((Paramètres!$C$5="Assujettie"),1/(1+Paramètres!$C$6),1)-Paramètres!$C$24+IF(E17>=Paramètres!$C$16,0,Paramètres!$C$15*IF((Paramètres!$C$5="Assujettie"),1/(1+Paramètres!$C$6),1)*(1-Paramètres!$C$13)-Paramètres!$C$15*Paramètres!$C$11)) -> 13.067332 | O17: =G17*Paramètres!$C$25 -> 32.937004 | P17: =IF(G17=0,"Prix fournisseur manquant",IF(N17<0,"Perte si vendu seul",IF(L17<Paramètres!$C$26,"Marge faible","OK"))) -> OK
A18: Onsha | B18: Coffret Douche Thermale Coréen (Home) | C18: ONSHA-COFFRET-HOME | D18: Pommeau (12) + set Home (13) | E18: 79.9 | F18: ='Tarifs Onsha-Sullab'!$N$16+'Tarifs Onsha-Sullab'!$N$17 -> 22.532 | G18: ='Tarifs Onsha-Sullab'!$O$16+'Tarifs Onsha-Sullab'!$O$17 -> 28.200964 | H18: =IF((Paramètres!$C$5="Assujettie"),E18/(1+Paramètres!$C$6),E18) -> 66.583333 | I18: =E18*Paramètres!$C$11 -> 1.1985 | J18: =H18*Paramètres!$C$13 -> 0 | K18: =IF(G18=0,0,H18-G18-I18-J18) -> 37.18387 | L18: =IF(H18=0,0,K18/H18) -> 0.55845611 | M18: =IF(G18=0,0,E18/G18) -> 2.8332365 | N18: =IF(G18=0,0,K18-Paramètres!$C$12-(Paramètres!$C$14+Paramètres!$C$22+Paramètres!$C$23)*IF((Paramètres!$C$5="Assujettie"),1/(1+Paramètres!$C$6),1)-Paramètres!$C$24+IF(E18>=Paramètres!$C$16,0,Paramètres!$C$15*IF((Paramètres!$C$5="Assujettie"),1/(1+Paramètres!$C$6),1)*(1-Paramètres!$C$13)-Paramètres!$C$15*Paramètres!$C$11)) -> 36.762036 | O18: =G18*Paramètres!$C$25 -> 84.602891 | P18: =IF(G18=0,"Prix fournisseur manquant",IF(N18<0,"Perte si vendu seul",IF(L18<Paramètres!$C$26,"Marge faible","OK"))) -> OK
A19: Onsha | B19: Coffret Douche Thermale Coréen (Nomade) | C19: ONSHA-COFFRET-NOMADE | D19: Douchette (1) + sédiments x3 (3) + set Nomade (6) | E19: 59.9 | F19: ='Tarifs Onsha-Sullab'!$N$5+'Tarifs Onsha-Sullab'!$N$7+'Tarifs Onsha-Sullab'!$N$10 -> 17.974 | G19: ='Tarifs Onsha-Sullab'!$O$5+'Tarifs Onsha-Sullab'!$O$7+'Tarifs Onsha-Sullab'!$O$10 -> 22.496189 | H19: =IF((Paramètres!$C$5="Assujettie"),E19/(1+Paramètres!$C$6),E19) -> 49.916667 | I19: =E19*Paramètres!$C$11 -> 0.8985 | J19: =H19*Paramètres!$C$13 -> 0 | K19: =IF(G19=0,0,H19-G19-I19-J19) -> 26.521978 | L19: =IF(H19=0,0,K19/H19) -> 0.5313251 | M19: =IF(G19=0,0,E19/G19) -> 2.6626733 | N19: =IF(G19=0,0,K19-Paramètres!$C$12-(Paramètres!$C$14+Paramètres!$C$22+Paramètres!$C$23)*IF((Paramètres!$C$5="Assujettie"),1/(1+Paramètres!$C$6),1)-Paramètres!$C$24+IF(E19>=Paramètres!$C$16,0,Paramètres!$C$15*IF((Paramètres!$C$5="Assujettie"),1/(1+Paramètres!$C$6),1)*(1-Paramètres!$C$13)-Paramètres!$C$15*Paramètres!$C$11)) -> 26.100145 | O19: =G19*Paramètres!$C$25 -> 67.488566 | P19: =IF(G19=0,"Prix fournisseur manquant",IF(N19<0,"Perte si vendu seul",IF(L19<Paramètres!$C$26,"Marge faible","OK"))) -> OK
A20: Sullab | B20: Filtre Robinet Lavabo | C20: SULLAB-ROBINET | D20: Réf. 19 | E20: 25.9 | F20: ='Tarifs Onsha-Sullab'!$N$23 -> 4.644 | G20: ='Tarifs Onsha-Sullab'!$O$23 -> 5.8124124 | H20: =IF((Paramètres!$C$5="Assujettie"),E20/(1+Paramètres!$C$6),E20) -> 21.583333 | I20: =E20*Paramètres!$C$11 -> 0.3885 | J20: =H20*Paramètres!$C$13 -> 0 | K20: =IF(G20=0,0,H20-G20-I20-J20) -> 15.382421 | L20: =IF(H20=0,0,K20/H20) -> 0.71269904 | M20: =IF(G20=0,0,E20/G20) -> 4.4559811 | N20: =IF(G20=0,0,K20-Paramètres!$C$12-(Paramètres!$C$14+Paramètres!$C$22+Paramètres!$C$23)*IF((Paramètres!$C$5="Assujettie"),1/(1+Paramètres!$C$6),1)-Paramètres!$C$24+IF(E20>=Paramètres!$C$16,0,Paramètres!$C$15*IF((Paramètres!$C$5="Assujettie"),1/(1+Paramètres!$C$6),1)*(1-Paramètres!$C$13)-Paramètres!$C$15*Paramètres!$C$11)) -> 14.960588 | O20: =G20*Paramètres!$C$25 -> 17.437237 | P20: =IF(G20=0,"Prix fournisseur manquant",IF(N20<0,"Perte si vendu seul",IF(L20<Paramètres!$C$26,"Marge faible","OK"))) -> OK
A21: Sullab | B21: Lot 3 Sédiments (robinet) | C21: SULLAB-SEDIMENT-X3 | D21: Réf. 20 | E21: 11.9 | F21: ='Tarifs Onsha-Sullab'!$N$24 -> 1.978 | G21: ='Tarifs Onsha-Sullab'!$O$24 -> 2.4756571 | H21: =IF((Paramètres!$C$5="Assujettie"),E21/(1+Paramètres!$C$6),E21) -> 9.9166667 | I21: =E21*Paramètres!$C$11 -> 0.1785 | J21: =H21*Paramètres!$C$13 -> 0 | K21: =IF(G21=0,0,H21-G21-I21-J21) -> 7.2625095 | L21: =IF(H21=0,0,K21/H21) -> 0.7323539 | M21: =IF(G21=0,0,E21/G21) -> 4.8068046 | N21: =IF(G21=0,0,K21-Paramètres!$C$12-(Paramètres!$C$14+Paramètres!$C$22+Paramètres!$C$23)*IF((Paramètres!$C$5="Assujettie"),1/(1+Paramètres!$C$6),1)-Paramètres!$C$24+IF(E21>=Paramètres!$C$16,0,Paramètres!$C$15*IF((Paramètres!$C$5="Assujettie"),1/(1+Paramètres!$C$6),1)*(1-Paramètres!$C$13)-Paramètres!$C$15*Paramètres!$C$11)) -> 6.8406762 | O21: =G21*Paramètres!$C$25 -> 7.4269714 | P21: =IF(G21=0,"Prix fournisseur manquant",IF(N21<0,"Perte si vendu seul",IF(L21<Paramètres!$C$26,"Marge faible","OK"))) -> OK
A22: SHIFT | B22: Coffret Soin Douche Coréenne | C22: SHIFT-COFFRET-SOIN | D22: Pommeau avec 1 filtre (S1) + 1 capsule (1/6 de S4) (à confirmer) | E22: 59.9 | F22: ='Tarifs Shift'!$K$5+1/6*'Tarifs Shift'!$K$8 -> 13.401667 | G22: ='Tarifs Shift'!$L$5+1/6*'Tarifs Shift'!$L$8 -> 15.481718 | H22: =IF((Paramètres!$C$5="Assujettie"),E22/(1+Paramètres!$C$6),E22) -> 49.916667 | I22: =E22*Paramètres!$C$11 -> 0.8985 | J22: =H22*Paramètres!$C$13 -> 0 | K22: =IF(G22=0,0,H22-G22-I22-J22) -> 33.536449 | L22: =IF(H22=0,0,K22/H22) -> 0.67184873 | M22: =IF(G22=0,0,E22/G22) -> 3.8690797 | N22: =IF(G22=0,0,K22-Paramètres!$C$12-(Paramètres!$C$14+Paramètres!$C$22+Paramètres!$C$23)*IF((Paramètres!$C$5="Assujettie"),1/(1+Paramètres!$C$6),1)-Paramètres!$C$24+IF(E22>=Paramètres!$C$16,0,Paramètres!$C$15*IF((Paramètres!$C$5="Assujettie"),1/(1+Paramètres!$C$6),1)*(1-Paramètres!$C$13)-Paramètres!$C$15*Paramètres!$C$11)) -> 33.114616 | O22: =G22*Paramètres!$C$25 -> 46.445153 | P22: =IF(G22=0,"Prix fournisseur manquant",IF(N22<0,"Perte si vendu seul",IF(L22<Paramètres!$C$26,"Marge faible","OK"))) -> OK
A23: SHIFT | B23: Coffret Douche & Aromathérapie | C23: SHIFT-COFFRET-AROMA-* | D23: Aroma Therapy Shower Kit (S3) (à confirmer : tu as commandé des Trial Kits) | E23: 109.9 | F23: ='Tarifs Shift'!$K$7 -> 30.1 | G23: ='Tarifs Shift'!$L$7 -> 34.771772 | H23: =IF((Paramètres!$C$5="Assujettie"),E23/(1+Paramètres!$C$6),E23) -> 91.583333 | I23: =E23*Paramètres!$C$11 -> 1.6485 | J23: =H23*Paramètres!$C$13 -> 0 | K23: =IF(G23=0,0,H23-G23-I23-J23) -> 55.163061 | L23: =IF(H23=0,0,K23/H23) -> 0.60232642 | M23: =IF(G23=0,0,E23/G23) -> 3.1606097 | N23: =IF(G23=0,0,K23-Paramètres!$C$12-(Paramètres!$C$14+Paramètres!$C$22+Paramètres!$C$23)*IF((Paramètres!$C$5="Assujettie"),1/(1+Paramètres!$C$6),1)-Paramètres!$C$24+IF(E23>=Paramètres!$C$16,0,Paramètres!$C$15*IF((Paramètres!$C$5="Assujettie"),1/(1+Paramètres!$C$6),1)*(1-Paramètres!$C$13)-Paramètres!$C$15*Paramètres!$C$11)) -> 49.913061 | O23: =G23*Paramètres!$C$25 -> 104.31532 | P23: =IF(G23=0,"Prix fournisseur manquant",IF(N23<0,"Perte si vendu seul",IF(L23<Paramètres!$C$26,"Marge faible","OK"))) -> OK
A24: SHIFT | B24: Pack 3 Filtres à Sédiments (Pure Water) | C24: SHIFT-PUREWATER-X3 | D24: Boîte de 3 filtres (S5) | E24: 25.9 | F24: ='Tarifs Shift'!$K$9 -> 4.73 | G24: ='Tarifs Shift'!$L$9 -> 5.4641357 | H24: =IF((Paramètres!$C$5="Assujettie"),E24/(1+Paramètres!$C$6),E24) -> 21.583333 | I24: =E24*Paramètres!$C$11 -> 0.3885 | J24: =H24*Paramètres!$C$13 -> 0 | K24: =IF(G24=0,0,H24-G24-I24-J24) -> 15.730698 | L24: =IF(H24=0,0,K24/H24) -> 0.72883541 | M24: =IF(G24=0,0,E24/G24) -> 4.7399994 | N24: =IF(G24=0,0,K24-Paramètres!$C$12-(Paramètres!$C$14+Paramètres!$C$22+Paramètres!$C$23)*IF((Paramètres!$C$5="Assujettie"),1/(1+Paramètres!$C$6),1)-Paramètres!$C$24+IF(E24>=Paramètres!$C$16,0,Paramètres!$C$15*IF((Paramètres!$C$5="Assujettie"),1/(1+Paramètres!$C$6),1)*(1-Paramètres!$C$13)-Paramètres!$C$15*Paramètres!$C$11)) -> 15.308864 | O24: =G24*Paramètres!$C$25 -> 16.392407 | P24: =IF(G24=0,"Prix fournisseur manquant",IF(N24<0,"Perte si vendu seul",IF(L24<Paramètres!$C$26,"Marge faible","OK"))) -> OK
A25: SHIFT | B25: Pack 6 Capsules Soin & Aromathérapie | C25: SHIFT-CAPS6-* | D25: Boîte de 6 capsules (S4) | E25: 32.9 | F25: ='Tarifs Shift'!$K$8 -> 5.59 | G25: ='Tarifs Shift'!$L$8 -> 6.4576149 | H25: =IF((Paramètres!$C$5="Assujettie"),E25/(1+Paramètres!$C$6),E25) -> 27.416667 | I25: =E25*Paramètres!$C$11 -> 0.4935 | J25: =H25*Paramètres!$C$13 -> 0 | K25: =IF(G25=0,0,H25-G25-I25-J25) -> 20.465552 | L25: =IF(H25=0,0,K25/H25) -> 0.74646389 | M25: =IF(G25=0,0,E25/G25) -> 5.0947603 | N25: =IF(G25=0,0,K25-Paramètres!$C$12-(Paramètres!$C$14+Paramètres!$C$22+Paramètres!$C$23)*IF((Paramètres!$C$5="Assujettie"),1/(1+Paramètres!$C$6),1)-Paramètres!$C$24+IF(E25>=Paramètres!$C$16,0,Paramètres!$C$15*IF((Paramètres!$C$5="Assujettie"),1/(1+Paramètres!$C$6),1)*(1-Paramètres!$C$13)-Paramètres!$C$15*Paramètres!$C$11)) -> 20.043718 | O25: =G25*Paramètres!$C$25 -> 19.372845 | P25: =IF(G25=0,"Prix fournisseur manquant",IF(N25<0,"Perte si vendu seul",IF(L25<Paramètres!$C$26,"Marge faible","OK"))) -> OK

Sheet Simulateur commande
B2: Simulateur de commande
B3: Choisis jusqu'à 6 produits dans la liste et leur quantité : tu vois ce qu'il te reste après tous les frais.
B5: Produit | C5: Quantité | D5: Prix TTC total (€) | E5: Coût de revient total (€)
B6: Starter Home | C6: 1 | D6: =IF(B6="",0,C6*INDEX('Marges produits'!$E$5:$E$25,MATCH(B6,'Marges produits'!$B$5:$B$25,0))) -> 49.9 | E6: =IF(B6="",0,C6*INDEX('Marges produits'!$G$5:$G$25,MATCH(B6,'Marges produits'!$B$5:$B$25,0))) -> 14.208119
B7: Filtre Thermal Vitaminé (Home) | C7: 2 | D7: =IF(B7="",0,C7*INDEX('Marges produits'!$E$5:$E$25,MATCH(B7,'Marges produits'!$B$5:$B$25,0))) -> 25.8 | E7: =IF(B7="",0,C7*INDEX('Marges produits'!$G$5:$G$25,MATCH(B7,'Marges produits'!$B$5:$B$25,0))) -> 10.117903
D8: =IF(B8="",0,C8*INDEX('Marges produits'!$E$5:$E$25,MATCH(B8,'Marges produits'!$B$5:$B$25,0))) -> 0 | E8: =IF(B8="",0,C8*INDEX('Marges produits'!$G$5:$G$25,MATCH(B8,'Marges produits'!$B$5:$B$25,0))) -> 0
D9: =IF(B9="",0,C9*INDEX('Marges produits'!$E$5:$E$25,MATCH(B9,'Marges produits'!$B$5:$B$25,0))) -> 0 | E9: =IF(B9="",0,C9*INDEX('Marges produits'!$G$5:$G$25,MATCH(B9,'Marges produits'!$B$5:$B$25,0))) -> 0
D10: =IF(B10="",0,C10*INDEX('Marges produits'!$E$5:$E$25,MATCH(B10,'Marges produits'!$B$5:$B$25,0))) -> 0 | E10: =IF(B10="",0,C10*INDEX('Marges produits'!$G$5:$G$25,MATCH(B10,'Marges produits'!$B$5:$B$25,0))) -> 0
D11: =IF(B11="",0,C11*INDEX('Marges produits'!$E$5:$E$25,MATCH(B11,'Marges produits'!$B$5:$B$25,0))) -> 0 | E11: =IF(B11="",0,C11*INDEX('Marges produits'!$G$5:$G$25,MATCH(B11,'Marges produits'!$B$5:$B$25,0))) -> 0
B13: Total payé par la cliente, produits (TTC) | D13: =SUM(D6:D11) -> 75.7 | F13: Astuce : compare un panier d'un seul article avec un panier de 2-3 articles. Les frais fixes (colis, emballage, paiement) pèsent beaucoup moins sur un gros panier.
B14: Livraison payée par la cliente (TTC) | D14: =IF(OR(D13=0,D13>=Paramètres!$C$16),0,Paramètres!$C$15) -> 5.9
B15: Chiffre d'affaires encaissé (hors TVA si assujettie) | D15: =IF((Paramètres!$C$5="Assujettie"),(D13+D14)/(1+Paramètres!$C$6),D13+D14) -> 68
B16: − Coût de revient des produits | D16: =-SUM(E6:E11) -> -24.326022
B17: − Frais de paiement | D17: =IF(D13=0,0,-((D13+D14)*Paramètres!$C$11+Paramètres!$C$12)) -> -1.474
B18: − Charges proportionnelles au CA | D18: =-D15*Paramètres!$C$13 -> 0
B19: − Expédition | D19: =IF(D13=0,0,-Paramètres!$C$14*IF((Paramètres!$C$5="Assujettie"),1/(1+Paramètres!$C$6),1)) -> -3.3333333
B20: − Emballage et cadeau | D20: =IF(D13=0,0,-(Paramètres!$C$22+Paramètres!$C$23)*IF((Paramètres!$C$5="Assujettie"),1/(1+Paramètres!$C$6),1)) -> -1.6666667
B21: − Publicité | D21: =IF(D13=0,0,-Paramètres!$C$24) -> 0
B22: CE QU'IL TE RESTE SUR CETTE COMMANDE | D22: =SUM(D15:D21) -> 37.199978
B23: Soit en % du chiffre d'affaires | D23: =IF(D15=0,0,D22/D15) -> 0.5470585

Sheet Seuil de rentabilité
B2: Frais fixes du mois et seuil de rentabilité
B3: Mets tes vrais abonnements, TTC (exemples en jaune). Mets 0 pour ce que tu n'as pas. La TVA est retirée automatiquement.
B5: Frais fixe mensuel | C5: Montant (€) | D5: Remarque
B6: Abonnement Shopify (annuel ÷ 12) | C6: 25 | D6: D'après toi : environ 300 € payés à l'année.
B7: Applications Shopify | C7: 0 | D7: Avis, bundles, traduction…
B8: Nom de domaine (coût annuel ÷ 12) | C8: 1.5 | D8: Exemple.
B9: Klaviyo / emailing | C9: 0 | D9: Gratuit jusqu'à un certain nombre de contacts.
B10: Canva, Metricool, outils de contenu | C10: 0
B11: Banque professionnelle | C11: 0
B12: Assurance responsabilité civile pro | C12: 0 | D12: Recommandée pour la vente de produits.
B13: Comptable / logiciel de facturation | C13: 0
B14: Stockage, divers | C14: 0
B15: Total des frais fixes par mois (hors TVA si récupérable) | C15: =SUM(C6:C14)*IF((Paramètres!$C$5="Assujettie"),1/(1+Paramètres!$C$6),1) -> 22.083333
B17: Ce qu'il te reste en moyenne par commande (€) | C17: ='Simulateur commande'!D22 -> 37.199978 | D17: Repris du simulateur. Tu peux remplacer par ta vraie moyenne une fois que tu as des ventes.
B18: Commandes nécessaires par mois pour couvrir les frais fixes | C18: =IF(C17<=0,"Marge négative",ROUNDUP(C15/C17,0)) -> 1
B19: Soit environ par semaine | C19: =IF(ISNUMBER(C18),ROUNDUP(C18/4.33,0),"-") -> 1

Sheet Coffrets Onsha
A1: Coffrets Onsha proposés · pour vendre les recharges par lot plutôt qu'à l'unité
A2: Propositions à tester, pas encore créées sur Shopify. Le prix proposé (bleu) est modifiable : tout se recalcule. Coûts et prix unitaires repris de l'onglet Marges produits.
A4: Coffret | B4: Objectif | C4: Composition | D4: Valeur si acheté à l'unité (€) | E4: Prix proposé TTC (€) | F4: Économie cliente | G4: Coût de revient (€) | H4: CA hors TVA (€) | I4: Marge produit (€) | J4: Taux de marge | K4: Il te reste si commandé seul (€) | L4: Comparaison : il te reste avec 1 seule unité (€) | M4: Livraison offerte ?
A5: Duo Filtres Home | B5: Faire racheter 2 filtres au lieu d'1 | C5: 2 filtres thermaux Home au choix | D5: =2*'Marges produits'!$E$11 -> 25.8 | E5: 23.9 | F5: =IF(D5=0,0,1-E5/D5) -> 0.073643411 | G5: =2*'Marges produits'!$G$11 -> 10.117903 | H5: =IF((Paramètres!$C$5="Assujettie"),E5/(1+Paramètres!$C$6),E5) -> 19.916667 | I5: =H5-G5-E5*Paramètres!$C$11-H5*Paramètres!$C$13 -> 9.4402636 | J5: =IF(H5=0,0,I5/H5) -> 0.47398813 | K5: =I5-Paramètres!$C$12-(Paramètres!$C$14+Paramètres!$C$22+Paramètres!$C$23)*IF((Paramètres!$C$5="Assujettie"),1/(1+Paramètres!$C$6),1)-Paramètres!$C$24+IF(E5>=Paramètres!$C$16,0,Paramètres!$C$15*IF((Paramètres!$C$5="Assujettie"),1/(1+Paramètres!$C$6),1)*(1-Paramètres!$C$13)-Paramètres!$C$15*Paramètres!$C$11) -> 9.0184303 | L5: ='Marges produits'!$N$11 -> 5.0757151 | M5: =IF(E5>=Paramètres!$C$16,"Oui","Non") -> Non
A6: Rituel Saison Home | B6: Recharge pour plusieurs mois, panier plus élevé | C6: 4 filtres thermaux Home (au choix ou 1 de chaque senteur) | D6: =4*'Marges produits'!$E$11 -> 51.6 | E6: 44.9 | F6: =IF(D6=0,0,1-E6/D6) -> 0.12984496 | G6: =4*'Marges produits'!$G$11 -> 20.235806 | H6: =IF((Paramètres!$C$5="Assujettie"),E6/(1+Paramètres!$C$6),E6) -> 37.416667 | I6: =H6-G6-E6*Paramètres!$C$11-H6*Paramètres!$C$13 -> 16.507361 | J6: =IF(H6=0,0,I6/H6) -> 0.44117667 | K6: =I6-Paramètres!$C$12-(Paramètres!$C$14+Paramètres!$C$22+Paramètres!$C$23)*IF((Paramètres!$C$5="Assujettie"),1/(1+Paramètres!$C$6),1)-Paramètres!$C$24+IF(E6>=Paramètres!$C$16,0,Paramètres!$C$15*IF((Paramètres!$C$5="Assujettie"),1/(1+Paramètres!$C$6),1)*(1-Paramètres!$C$13)-Paramètres!$C$15*Paramètres!$C$11) -> 16.085527 | L6: ='Marges produits'!$N$11 -> 5.0757151 | M6: =IF(E6>=Paramètres!$C$16,"Oui","Non") -> Non
A7: Trio Capsules Nomade | B7: Remplacer l'achat d'une capsule seule (en perte) | C7: 3 capsules thermales Nomade au choix | D7: =3*'Marges produits'!$E$13 -> 20.7 | E7: 17.9 | F7: =IF(D7=0,0,1-E7/D7) -> 0.1352657 | G7: =3*'Marges produits'!$G$13 -> 7.4269714 | H7: =IF((Paramètres!$C$5="Assujettie"),E7/(1+Paramètres!$C$6),E7) -> 14.916667 | I7: =H7-G7-E7*Paramètres!$C$11-H7*Paramètres!$C$13 -> 7.2211953 | J7: =IF(H7=0,0,I7/H7) -> 0.48410248 | K7: =I7-Paramètres!$C$12-(Paramètres!$C$14+Paramètres!$C$22+Paramètres!$C$23)*IF((Paramètres!$C$5="Assujettie"),1/(1+Paramètres!$C$6),1)-Paramètres!$C$24+IF(E7>=Paramètres!$C$16,0,Paramètres!$C$15*IF((Paramètres!$C$5="Assujettie"),1/(1+Paramètres!$C$6),1)*(1-Paramètres!$C$13)-Paramètres!$C$15*Paramètres!$C$11) -> 6.7993619 | L7: ='Marges produits'!$N$13 -> 2.7490095 | M7: =IF(E7>=Paramètres!$C$16,"Oui","Non") -> Non
A8: Rituel Saison Nomade | B8: Recharge pour plusieurs mois | C8: 6 capsules thermales Nomade au choix | D8: =6*'Marges produits'!$E$13 -> 41.4 | E8: 34.9 | F8: =IF(D8=0,0,1-E8/D8) -> 0.15700483 | G8: =6*'Marges produits'!$G$13 -> 14.853943 | H8: =IF((Paramètres!$C$5="Assujettie"),E8/(1+Paramètres!$C$6),E8) -> 29.083333 | I8: =H8-G8-E8*Paramètres!$C$11-H8*Paramètres!$C$13 -> 13.705891 | J8: =IF(H8=0,0,I8/H8) -> 0.47126271 | K8: =I8-Paramètres!$C$12-(Paramètres!$C$14+Paramètres!$C$22+Paramètres!$C$23)*IF((Paramètres!$C$5="Assujettie"),1/(1+Paramètres!$C$6),1)-Paramètres!$C$24+IF(E8>=Paramètres!$C$16,0,Paramètres!$C$15*IF((Paramètres!$C$5="Assujettie"),1/(1+Paramètres!$C$6),1)*(1-Paramètres!$C$13)-Paramètres!$C$15*Paramètres!$C$11) -> 13.284057 | L8: ='Marges produits'!$N$13 -> 2.7490095 | M8: =IF(E8>=Paramètres!$C$16,"Oui","Non") -> Non
A9: Douchette Habillée | B9: Vendre la housse avec la douchette (housse seule en perte) | C9: 1 douchette filtrante + 1 housse au choix | D9: =1*'Marges produits'!$E$6+1*'Marges produits'!$E$8 -> 33.8 | E9: 29.9 | F9: =IF(D9=0,0,1-E9/D9) -> 0.11538462 | G9: =1*'Marges produits'!$G$6+1*'Marges produits'!$G$8 -> 10.979001 | H9: =IF((Paramètres!$C$5="Assujettie"),E9/(1+Paramètres!$C$6),E9) -> 24.916667 | I9: =H9-G9-E9*Paramètres!$C$11-H9*Paramètres!$C$13 -> 13.489165 | J9: =IF(H9=0,0,I9/H9) -> 0.54137119 | K9: =I9-Paramètres!$C$12-(Paramètres!$C$14+Paramètres!$C$22+Paramètres!$C$23)*IF((Paramètres!$C$5="Assujettie"),1/(1+Paramètres!$C$6),1)-Paramètres!$C$24+IF(E9>=Paramètres!$C$16,0,Paramètres!$C$15*IF((Paramètres!$C$5="Assujettie"),1/(1+Paramètres!$C$6),1)*(1-Paramètres!$C$13)-Paramètres!$C$15*Paramètres!$C$11) -> 13.067332 | L9: ='Marges produits'!$N$8 -> 3.6970878 | M9: =IF(E9>=Paramètres!$C$16,"Oui","Non") -> Non
A10: Duo Recharges Douchette | B10: Fidéliser les clientes de la douchette | C10: 2 boîtes de 3 filtres sédiment (6 filtres) | D10: =2*'Marges produits'!$E$7 -> 27.8 | E10: 24.9 | F10: =IF(D10=0,0,1-E10/D10) -> 0.10431655 | G10: =2*'Marges produits'!$G$7 -> 9.0415304 | H10: =IF((Paramètres!$C$5="Assujettie"),E10/(1+Paramètres!$C$6),E10) -> 20.75 | I10: =H10-G10-E10*Paramètres!$C$11-H10*Paramètres!$C$13 -> 11.33497 | J10: =IF(H10=0,0,I10/H10) -> 0.5462636 | K10: =I10-Paramètres!$C$12-(Paramètres!$C$14+Paramètres!$C$22+Paramètres!$C$23)*IF((Paramètres!$C$5="Assujettie"),1/(1+Paramètres!$C$6),1)-Paramètres!$C$24+IF(E10>=Paramètres!$C$16,0,Paramètres!$C$15*IF((Paramètres!$C$5="Assujettie"),1/(1+Paramètres!$C$6),1)*(1-Paramètres!$C$13)-Paramètres!$C$15*Paramètres!$C$11) -> 10.913136 | L10: ='Marges produits'!$N$7 -> 6.4322348 | M10: =IF(E10>=Paramètres!$C$16,"Oui","Non") -> Non
A11: Set Découverte Home + 2 filtres | B11: Faire monter le panier dès le premier achat | C11: Set Découverte Home (coque + 4 filtres) + 2 filtres au choix | D11: =1*'Marges produits'!$E$16+2*'Marges produits'!$E$11 -> 85.7 | E11: 74.9 | F11: =IF(D11=0,0,1-E11/D11) -> 0.126021 | G11: =1*'Marges produits'!$G$16+2*'Marges produits'!$G$11 -> 31.645356 | H11: =IF((Paramètres!$C$5="Assujettie"),E11/(1+Paramètres!$C$6),E11) -> 62.416667 | I11: =H11-G11-E11*Paramètres!$C$11-H11*Paramètres!$C$13 -> 29.64781 | J11: =IF(H11=0,0,I11/H11) -> 0.4749983 | K11: =I11-Paramètres!$C$12-(Paramètres!$C$14+Paramètres!$C$22+Paramètres!$C$23)*IF((Paramètres!$C$5="Assujettie"),1/(1+Paramètres!$C$6),1)-Paramètres!$C$24+IF(E11>=Paramètres!$C$16,0,Paramètres!$C$15*IF((Paramètres!$C$5="Assujettie"),1/(1+Paramètres!$C$6),1)*(1-Paramètres!$C$13)-Paramètres!$C$15*Paramètres!$C$11) -> 29.225977 | L11: ='Marges produits'!$N$16 -> 27.06888 | M11: =IF(E11>=Paramètres!$C$16,"Oui","Non") -> Non
A12: Set Découverte Nomade + 3 capsules | B12: Faire monter le panier dès le premier achat | C12: Set Découverte Nomade (coque + 4 capsules) + 3 capsules au choix | D12: =1*'Marges produits'!$E$17+3*'Marges produits'!$E$13 -> 50.6 | E12: 44.9 | F12: =IF(D12=0,0,1-E12/D12) -> 0.11264822 | G12: =1*'Marges produits'!$G$17+3*'Marges produits'!$G$13 -> 18.405973 | H12: =IF((Paramètres!$C$5="Assujettie"),E12/(1+Paramètres!$C$6),E12) -> 37.416667 | I12: =H12-G12-E12*Paramètres!$C$11-H12*Paramètres!$C$13 -> 18.337194 | J12: =IF(H12=0,0,I12/H12) -> 0.49008091 | K12: =I12-Paramètres!$C$12-(Paramètres!$C$14+Paramètres!$C$22+Paramètres!$C$23)*IF((Paramètres!$C$5="Assujettie"),1/(1+Paramètres!$C$6),1)-Paramètres!$C$24+IF(E12>=Paramètres!$C$16,0,Paramètres!$C$15*IF((Paramètres!$C$5="Assujettie"),1/(1+Paramètres!$C$6),1)*(1-Paramètres!$C$13)-Paramètres!$C$15*Paramètres!$C$11) -> 17.915361 | L12: ='Marges produits'!$N$17 -> 13.067332 | M12: =IF(E12>=Paramètres!$C$16,"Oui","Non") -> Non
A14: Comment lire : la colonne « Il te reste si commandé seul » compte le colis, l'emballage, le cadeau et la livraison payée par la cliente. Compare-la à la dernière colonne : c'est ce que tu gagnes en plus en vendant le lot plutôt qu'une seule unité.
A15: Règle de prix utilisée : environ 7 à 16 % d'économie par rapport à l'unité. Assez pour donner envie, sans casser ta marge.
A16: Le cadeau à 3 € pèse beaucoup sur les petits paniers : mets 0 dans Paramètres pour voir l'effet, ou réserve-le aux commandes à partir de 40 €.
